pyunstuck/__init__.py
pyunstuck/cli.py
pyunstuck-1.1.0.dist-info/licenses/LICENSE
pyunstuck-1.1.0.dist-info/METADATA
pyunstuck-1.1.0.dist-info/WHEEL
pyunstuck-1.1.0.dist-info/entry_points.txt
pyunstuck-1.1.0.dist-info/top_level.txt
pyunstuck-1.1.0.dist-info/RECORD
