Metadata-Version: 2.4
Name: pyunstuck
Version: 1.1.0
Summary: A lifesaver for frozen Python scripts
Home-page: https://github.com/shuakami/pyunstuck
Author: shuakami
Author-email: shuakami@sdjz.wiki
Classifier: Development Status :: 4 - Beta
Classifier: Intended Audience :: Developers
Classifier: Topic :: Software Development :: Debuggers
Classifier: Programming Language :: Python :: 3.11
Classifier: License :: OSI Approved :: MIT License
Classifier: Operating System :: OS Independent
Requires-Python: >=3.11
License-File: LICENSE
Requires-Dist: psutil>=5.9.0
Requires-Dist: keyboard>=0.13.5
Dynamic: author
Dynamic: author-email
Dynamic: classifier
Dynamic: description
Dynamic: description-content-type
Dynamic: home-page
Dynamic: license-file
Dynamic: requires-dist
Dynamic: requires-python
Dynamic: summary
